{"nodes": [{"id": "wasm", "label": "wasm.py", "file_type": "code", "source_file": "test_generated_blockchain\\modules\\vm\\wasm.py", "source_location": "L1"}, {"id": "wasm_wasmruntime", "label": "WASMRuntime", "file_type": "code", "source_file": "test_generated_blockchain\\modules\\vm\\wasm.py", "source_location": "L3"}, {"id": "vminterface", "label": "VMInterface", "file_type": "code", "source_file": "", "source_location": ""}, {"id": "wasm_wasmruntime_deploy_contract", "label": ".deploy_contract()", "file_type": "code", "source_file": "test_generated_blockchain\\modules\\vm\\wasm.py", "source_location": "L7"}, {"id": "wasm_wasmruntime_execute_transaction", "label": ".execute_transaction()", "file_type": "code", "source_file": "test_generated_blockchain\\modules\\vm\\wasm.py", "source_location": "L14"}, {"id": "wasm_rationale_4", "label": "Executes WebAssembly (WASM) smart contracts.", "file_type": "rationale", "source_file": "test_generated_blockchain\\modules\\vm\\wasm.py", "source_location": "L4"}], "edges": [{"source": "wasm", "target": "interfaces_vm", "relation": "imports_from", "confidence": "EXTRACTED", "source_file": "test_generated_blockchain\\modules\\vm\\wasm.py", "source_location": "L1", "weight": 1.0}, {"source": "wasm", "target": "wasm_wasmruntime", "relation": "contains", "confidence": "EXTRACTED", "source_file": "test_generated_blockchain\\modules\\vm\\wasm.py", "source_location": "L3", "weight": 1.0}, {"source": "wasm_wasmruntime", "target": "vminterface", "relation": "inherits", "confidence": "EXTRACTED", "source_file": "test_generated_blockchain\\modules\\vm\\wasm.py", "source_location": "L3", "weight": 1.0}, {"source": "wasm_wasmruntime", "target": "wasm_wasmruntime_deploy_contract", "relation": "method", "confidence": "EXTRACTED", "source_file": "test_generated_blockchain\\modules\\vm\\wasm.py", "source_location": "L7", "weight": 1.0}, {"source": "wasm_wasmruntime", "target": "wasm_wasmruntime_execute_transaction", "relation": "method", "confidence": "EXTRACTED", "source_file": "test_generated_blockchain\\modules\\vm\\wasm.py", "source_location": "L14", "weight": 1.0}, {"source": "wasm_rationale_4", "target": "wasm_wasmruntime", "relation": "rationale_for", "confidence": "EXTRACTED", "source_file": "test_generated_blockchain\\modules\\vm\\wasm.py", "source_location": "L4", "weight": 1.0}]}